{
 "absolute_value": 0,
 "align_labels_right": 0,
 "creation": "2023-12-06 11:02:24.409367",
 "css": ".heading{\n    background-color:rgba(31,55,93,255);\n    padding:8px 0px;\n    text-align:center;\n    color:white;\n    font-weight:700;\n}\n.blue{\n    background-color:rgba(31,55,93,255);\n    color:white;\n}\n.flex-container {\n    display: flex;\n    justify-content: space-between;\n    width: 100%;\n}\n.left-div, .right-div {\n    flex: 1;\n    display: flex;\n}\n.col{\n    display:inline-block;\n}\n.row{\n    display:flex;\n}\ntable, th, td {\n  border: 2px solid black;\n    line-height: 0.4em;\n}\ntable{\n    margin-top:15px;\n}\n.border{\n    border:2px solid black;\n}\n.text-center{\n    justify-content:center;\n}\n.p{\n    font-size:10px;\n}\n.bold{\n    font-weight:bold;\n}",
 "custom_format": 1,
 "default_print_language": "en",
 "disabled": 0,
 "doc_type": "Way Bill",
 "docstatus": 0,
 "doctype": "Print Format",
 "font_size": 14,
 "html": "<div id=\"header-html\" style=\"margin-top:-40px\"   class=\"hidden-pdf\">\n  {% set letter_head = frappe.get_doc(\"Letter Head\", doc.letter_head) %}\n  {% if letter_head %}\n\t{{ letter_head.content }}\n  {% else %}\n\t<p>Letter head {{ doc.letter_head }} not found. Please define the letter head under print settings.</p>\n  {% endif %}\n</div>\n<div class=\"text-center\" style=\"margin-top:-20px\">\n<h1 class=\"heading\">Truck Way Bill</h1>\n<div class=\"\">\n    <div class=\"flex-container\">\n        <!-- Left Div -->\n        <div class=\"left-div border border-dark\">\n            <div class=\"blue px-2\"><h4>DATE</h4></div>\n            <h5 class=\"px-2\"><b>{{doc.date}}</b></h5>\n        </div>\n        <!-- Right Div -->\n        <div class=\"right-div border border-black\">\n            <div class=\"blue px-2 \"><h4>Waybill</h4></div>\n            <div class=\"px-2\"><h5 ><b>{{doc.waybill}}</b></h5></div>\n        </div>\n    </div>\n</div>\n <div class=text-center>\n     <table style=\"width:100%\">\n         <tr style=\"height:5px\">\n             <th style=\"color:white\"   class=\"blue  text-center\" colspan=\"2\"><b  style=\"color:white\">DELIVERY INFORMATION</b></th>\n         </tr>\n         <tr>\n             <td style=\"width:30%\">ON-BOARD FROM</td>\n             <td class=\"bold\">{{doc.on_board_from or '' }}</td>\n         </tr>\n          <tr>\n             <td>DESTINATION</td>\n             <td class=\"bold\">{{doc.destination or '' }}</td>\n         </tr>\n          <tr>\n             <td>TRUCK PLATE NO</td>\n             <td class=\"bold\">{{doc.truck_plate_no or '' }}</td>\n         </tr>\n          <tr>\n             <td>DRIVER NAME</td>\n             <td class=\"bold\">{{doc.driver_name or '' }}</td>\n         </tr>\n         <tr>\n             <td>DRIVER IQAMA NO</td>\n             <td class=\"bold\">{{doc.driver_iqama_no or '' }}</td>\n         </tr>\n         <tr>\n             <td>DRIVER MOBILE NO</td>\n             <td class=\"bold\">{{doc.driver_mobile_no or '' }}</td>\n         </tr>\n          <tr>\n             <td>DISPATCHED ON</td>\n             <td class=\"bold\">{{doc.dispatched_on or '' }}</td>\n         </tr>\n     </table>\n </div>\n <div class=\"row flex-container center mx-1\" >\n     <div class=\"border mx-2 \" style=\"width:350px\">\n         <div class=\"blue border\"><h4 class=\"text-center\">SHIPPER</h4></div>\n         <div>{{doc.shipper or ''}}</div>\n     </div>\n     <div class=\"border mx-3 \"  style=\"width:350px\">\n         <div class=\"blue border\"><h4 class=\"text-center\">CONSIGNEE</h4></div>\n         <div>{{doc.consignee or ''}}</div>\n     </div>\n </div>\n <div>\n     <table style=\"width:100%\">\n         <tr>\n         <th>KIND OF PKG</th>\n         <th>NUMBER OF PACKAGES</th>\n         <th>WEIGHT</th>\n         <th>VOLUME</th>\n         <th>REMARKS</th>\n         </tr>\n            {% for item in doc.wb_table %}\n         <tr>\n             <td>{{item.kind_of_pkg}}</td>\n             <td>{{item.number_of_packages}}</td>\n             <td>{{item.weight}}</td>\n             <td>{{item.volume}}</td>\n             <td>{{item.remarks or ''}}</td>\n         </tr>\n         {% endfor %}\n     </table>\n     <div>\n         <div class=\"blue text-center \"><b  style=\"color:white\">CONTACT PERSON: {{doc.contact_person or ''}}</b></div>\n         <div><p class=\"border\">We acting as forwarder is not liable for any shortage/damage that may happen during any stage of transportation or operation.The carrier or trucker's or 3rd party operators\u2019 liability may be limited and may not be sufficient to cover the loss. Therefore it is the responsibility of the owner of goods to insure the transport against all risk involved on a door to door basis</p></div>\n     </div>\n    <div style=\"display: flex;\">\n    <div class=\"border flex-container left-div\" style=\"margin-right: 50px;\">\n        <div class=\"blue p-2\">GOODS RECEIVED ON</div>\n        <!-- Apply text-align:left here -->\n        <div style=\"text-align: left;\">\n            <h5 class=\"text-center px-4\"><b>{{ doc.goods_received_on or ''}}</b></h5>\n        </div>\n    </div>\n    <div class=\"border flex-container right-div\" style=\"margin-left: 50px;\">\n        <div class=\"blue p-2\">TRUCK RELEASED ON</div>\n        <!-- Apply text-align:left here -->\n        <div style=\"text-align: left;\">\n            <h5 class=\"px-4\"><b>{{ doc.truck_released_on or ''}}</b></h5>\n        </div>\n    </div>\n</div>\n <div class=\" row  mx-3\">\n     <div style=\"width:300px;height:140px ; margin-right:35px\" class=\"border \">\n         <div class=\"blue  py-1\"><h6>I RECEIVED THE GOODS STATED ABOVE IN GOOD\nORDER AND CONDITION </h6></div>\n         <div></div>\n     </div>\n      <div style=\"width:300px;margin-left:35px \" class=\"border \">\n         <div class=\"blue py-2\"><h6>SEAL OF THE RECEIVER COMPANY</h6></div>\n         <div></div>\n     </div>\n </div>\n{% if letter_head and not no_letterhead -%}\n{% if print_settings.repeat_header_footer %}\n   <br>  <div style=\"marrgin:0\" class=\"footer-content\">{{footer}}\n        </div>\n{%- endif %}{%- endif %}",
 "idx": 0,
 "line_breaks": 0,
 "margin_bottom": 15.0,
 "margin_left": 15.0,
 "margin_right": 15.0,
 "margin_top": 15.0,
 "modified": "2023-12-19 15:00:26.747680",
 "modified_by": "Administrator",
 "module": "Logistics",
 "name": "Waybill",
 "owner": "Administrator",
 "page_number": "Hide",
 "print_format_builder": 0,
 "print_format_builder_beta": 0,
 "print_format_type": "Jinja",
 "raw_printing": 0,
 "show_section_headings": 0,
 "standard": "Yes"
}